value_at_risk/__init__.py
value_at_risk/exceptions.py
value_at_risk/support.py
value_at_risk-1.0.5.dist-info/METADATA
value_at_risk-1.0.5.dist-info/WHEEL
value_at_risk-1.0.5.dist-info/top_level.txt
value_at_risk-1.0.5.dist-info/RECORD
