Metadata-Version: 2.1
Name: value-at-risk
Version: 1.0.5
Summary: Value at Risk Calculator
Home-page: https://github.com/moodoid/value_at_risk
Author: moodoid
License: UNKNOWN
Keywords: Value-at-Risk Tool
Platform: UNKNOWN
Classifier: Intended Audience :: Developers
